DM3Loc/Genedata.py
DM3Loc/Multihead_predict.py
DM3Loc/Multihead_train.py
DM3Loc/__init__.py
DM3Loc/hier_attention_mask.py
DM3Loc/multihead_attention_model.py
DM3Loc/model/weights_fold_0.h5
DM3Loc/model/weights_fold_1.h5
DM3Loc/model/weights_fold_2.h5
DM3Loc/model/weights_fold_3.h5
DM3Loc/model/weights_fold_4.h5
DM3Loc/model/weights_fold_5.h5
DM3Loc/model/weights_fold_6.h5
DM3Loc/model/weights_fold_7.h5
DM3Loc/testdata/modified_multilabel_seq.fasta
DM3Loc/testdata/modified_multilabel_seq_nonredundent.fasta
DM3Loc/testdata/test.fasta
dm3loc-1.2.0.dist-info/LICENSE
dm3loc-1.2.0.dist-info/METADATA
dm3loc-1.2.0.dist-info/WHEEL
dm3loc-1.2.0.dist-info/top_level.txt
dm3loc-1.2.0.dist-info/RECORD
